core/DEFINITIONS.v
`ifndef _DEFINITIONS_V_
`define _DEFINITIONS_V_

// RV32IM INSTRUCTION SET CODES

// R-TYPE
`define INST_R_ALU                  7'b0110011
    // FUNCT3
    // I extension
    `define ADD_FUNCT3              3'b000
    `define SUB_FUNCT3              3'b000
    `define SLL_FUNCT3              3'b001
    `define SLT_FUNCT3              3'b010
    `define SLTU_FUNCT3             3'b011
    `define XOR_FUNCT3              3'b100
    `define SRL_FUNCT3              3'b101
    `define SRA_FUNCT3              3'b101
    `define OR_FUNCT3               3'b110
    `define AND_FUNCT3              3'b111
    // M extension
    `define MUL_FUNCT3              3'b000
    `define MULH_FUNCT3             3'b001
    `define MULHSU_FUNCT3           3'b010
    `define MULHU_FUNCT3            3'b011
    `define DIV_FUNCT3              3'b100
    `define DIVU_FUNCT3             3'b101
    `define REM_FUNCT3              3'b110
    `define REMU_FUNCT3             3'b110
    // FUNCT7
    // I extension
    `define ADD_FUNCT7              7'b0
    `define SUB_FUNCT7              7'b01000000
    `define SLL_FUNCT7              7'b0
    `define SLT_FUNCT7              7'b0
    `define SLTU_FUNCT7             7'b0
    `define XOR_FUNCT7              7'b0
    `define SRL_FUNCT7              7'b0
    `define SRA_FUNCT7              7'b01000000
    `define OR_FUNCT7               7'b0
    `define AND_FUNCT7              7'b0
    // M extension
    `define M_EXTENSION_FUNCT7      7'b0


// I-TYPE
`define INST_I_ALU                  7'b0010011
    // I extension
    `define ADDI_FUNCT3             3'b000
    `define SLTI_FUNCT3             3'b010
    `define SLTIU_FUNCT3            3'b011
    `define XORI_FUNCT3             3'b100
    `define ORI_FUNCT3              3'b110
    `define ANDI_FUNCT3             3'b111

`define INST_I_LOAD                 7'b0000011
    // I extension
    `define LB_FUNCT3               3'b000
    `define LH_FUNCT3               3'b001
    `define LW_FUNCT3               3'b010
    `define LBU_FUNCT3              3'b100
    `define LHU_FUNCT3              3'b101

`define INST_I_JALR                 7'b1100111
    // FUNCT3
    // I extension
    `define JALR_FUNCT3             3'b000

`define INST_I_SHIFT                7'b0010011
    // FUNCT3
    // I extension
    `define SLLI_FUNCT3             3'b001
    `define SRLI_FUNCT3             3'b101
    `define SRAI_FUNCT3             3'b101
    //FUNCT7
    // I extension
    `define SLLI_FUNCT7             7'b0
    `define SRLI_FUNCT7             7'b0
    `define SRAI_FUNCT7             7'b0100000

`define INST_I_FENCE                7'b0001111
    // FUNCT3
    `define FENCE_FUNCT3            3'b000
    `define FENCEI_FUNCT3           3'b001

`define INST_I_CALL_N_BREAK         7'b1110011
    // IMM values
    `define ECALL_IMM               12'b0
    `define EBREAK_IMM              12'b1    

`define INST_I_CSR                  7'b1110011
    //FUNCT3
    `define CSRRW_FUNCT3            3'b001
    `define CSRRS_FUNCT3            3'b010
    `define CSRRC_FUNCT3            3'b011
    // Immediate CSR
    `define CSRRWI_FUNCT3           3'b101
    `define CSRRSI_FUNCT3           3'b110
    `define CSRRCI_FUNCT3           3'b111

// S-TYPE
`define INST_S_STORE                7'b0100011
    // I extension
    `define SB_FUNCT3               3'b000
    `define SH_FUNCT3               3'b001
    `define SW_FUNCT3               3'b010


// U-TYPE
`define INST_U_LUI                  7'b0110111
`define INST_U_AUIPC                7'b0010111


// J-TYPE
`define INST_J_JAL                  7'b1101111


// B-TYPE
`define INST_B_BRANCH               7'b1100011
    // FUNCT3
    // I extension
    `define BEQ_FUNCT3              3'b000
    `define BNE_FUNCT3              3'b001
    `define BLT_FUNCT3              3'b100
    `define BGE_FUNCT3              3'b101
    `define BLTU_FUNCT3             3'b110
    `define BGEU_FUNCT3             3'b111

`endif

// END OF INSTRUCTION SET CODES

core/rv32_decoder.v
`include "../core/DEFINITIONS.v"

module decoder(
    input clk,
    input [31:0] instruction,

    output [31:0] decoded_value,
    output [4:0] rs1,
    output [4:0] rs2,
    output [4:0] rd,
    output [6:0] opcode,
    output [2:0] funct3,
    output [6:0] funct7,
    output shift_la_sel,        // logical or arithmetic shift select
    output [7:0] pred_succ,     // Fence instruction 
    output e_call_break,
    output trap
);

    localparam  R_TYPE = 3'b000,
                I_TYPE = 3'b001,
                S_TYPE = 3'b010,
                U_TYPE = 3'b011,
                J_TYPE = 3'b100,
                B_TYPE = 3'b111;


    reg [31:0] decoded_value_reg, decoded_value_next;
    reg [4:0] rs1_reg, rs2_reg, rs1_next, rs2_next, rd_reg, rd_next;
    reg [6:0] opcode_reg, opcode_next, funct7_reg, funct7_next;
    reg [2:0] funct3_reg, funct3_next;
    reg shift_la_sel_reg, e_call_break_reg, trap_reg;
    reg [7:0] pred_succ_reg;

    // assign output
    assign opcode = opcode_reg;
    assign funct3 = funct3_reg;
    assign funct7 = funct7_reg;
    assign decoded_value = decoded_value_reg;
    assign rs1 = rs1_reg;
    assign rs2 = rs2_reg;
    assign rd = rd_reg;
    assign shift_la_sel = shift_la_sel_reg;
    assign e_call_break = e_call_break_reg;
    assign trap = trap_reg;
    assign pred_succ = pred_succ_reg;

    wire [2:0] instruction_type;
    assign instruction_type =   (instruction[6:0] == `INST_R_ALU )     ? R_TYPE :
                                (
                                instruction[6:0]  == `INST_I_ALU   ||
                                instruction[6:0]  == `INST_I_JALR  ||
                                instruction[6:0]  == `INST_I_LOAD  ||
                                instruction[6:0]  == `INST_I_SHIFT ||
                                instruction[6:0]  == `INST_S_STORE ||
                                instruction[6:0]  == `INST_I_CSR   ||
                                instruction[6:0]  == `INST_I_FENCE ||
                                instruction[6:0]  == `INST_I_CALL_N_BREAK
                                )                                      ? I_TYPE :
                                ( 
                                instruction[6:0]  == `INST_U_LUI   ||
                                instruction[6:0]  == `INST_U_AUIPC
                                )                                      ? U_TYPE :
                                ( instruction[6:0]  == `INST_J_JAL)    ? J_TYPE : 
                                ( instruction[6:0]  == `INST_B_BRANCH) ? B_TYPE : 3'bz;

    // perform update of decoded information at posedge of clock only
    always @(posedge clk) begin
        decoded_value_reg <= decoded_value_next;
        rs1_reg <= rs1_next;
        rs2_reg <= rs2_next;
        rd_reg  <= rd_next;
        opcode_reg <= opcode_next;
        funct3_reg <= funct3_next;
        funct7_reg <= funct7_next;
        shift_la_sel_reg <= (opcode_reg == `INST_I_SHIFT && funct7_reg !== 7'bz) ? instruction[30] : 1'bz;
        e_call_break_reg <= (opcode_reg == `INST_I_CALL_N_BREAK && instruction[14:12] == 3'b0) ? instruction[20] : 1'bz;
        trap_reg <= (rd_next === 5'b00000) ? 1'b1 : 1'b0;
        pred_succ_reg <= (opcode_reg == `INST_I_FENCE) ? ( (instruction[14:12] == 3'b000) ? instruction[27:20] : 8'b0) : 8'bz;
    end

    // decode next available instruction
    always @(*) begin

        opcode_next = instruction[6:0];
        
        case(instruction_type)
            R_TYPE: begin
                decoded_value_next = 32'bz; // no information to be decoded
                rs1_next = instruction[19:15];
                rs2_next = instruction[24:20];
                rd_next = instruction[11:7];
                funct3_next = instruction[14:12];
                funct7_next = instruction[31:25];
            end

            I_TYPE: begin
                if (opcode_next == `INST_I_ALU || opcode_next == `INST_I_JALR || opcode_next == `INST_I_LOAD) begin
                    decoded_value_next = { {21{instruction[31]}}, instruction[30:20]};
                    rs1_next = instruction[19:15];
                    rs2_next = 5'bz;
                    rd_next = instruction[11:7];
                    funct3_next = instruction[14:12];
                    funct7_next = 7'bz;
                end
                else if (opcode_next == `INST_I_SHIFT) begin
                    decoded_value_next = { {27{instruction[31]}}, instruction[24:20]}; 
                    rs1_next = instruction[19:15];
                    rs2_next = instruction[24:20];
                    rd_next = instruction[11:7];
                    funct3_next = instruction[14:12];
                    funct7_next = instruction[31:25];    
                end
                else if (opcode_next == `INST_I_CSR && instruction[14:12] !== 3'b0) begin
                    if ( instruction[14] )  begin// instruction[14] differentiates imm. '1' -> imm : CSRRSI, CSRRWI, CSRRCI
                        decoded_value_next = { 27'b0 + instruction[19:15]};
                    end
                    else begin
                        decoded_value_next = { 20'b0 + instruction[31:20]};
                    end
                end
                else if (opcode_next == `INST_I_CALL_N_BREAK && instruction[14:12] == 3'b0) begin
                    rd_next = 5'b0;
                    funct3_next = 3'b0;
                    funct7_next = 7'bz;
                end
                else if (opcode_next == `INST_I_FENCE) begin
                    funct3_next = instruction[14:12];
                end
            end

            S_TYPE: begin
                decoded_value_next = { {21{instruction[31]}}, instruction[30:25], instruction[11:7]};
                rs1_next = instruction[19:15];
                rs2_next = instruction[24:20];
                rd_next = 5'bz;
                funct3_next = instruction[14:12];
                funct7_next = 7'bz;
            end

            U_TYPE: begin
                decoded_value_next = {instruction[31:12], 12'b0};
                rs1_next = 5'bz;
                rs2_next = 5'bz;
                rd_next = instruction[11:7];
                funct3_next = 3'bz;
                funct7_next = 7'bz;
            end

            J_TYPE: begin
                decoded_value_next = { {12{instruction[31]}}, instruction[19:12], instruction[20], instruction[30:21], 1'b0};
                rs1_next = 5'bz;
                rs2_next = 5'bz;
                rd_next = instruction[11:7];
                funct3_next = 3'bz;
                funct7_next = 7'bz;
            end

            B_TYPE: begin
                decoded_value_next = { {20{instruction[31]}}, instruction[7], instruction[30:25], instruction[11:8], 1'b0};
                rs1_next = instruction[19:15];
                rs2_next = instruction[24:20];
                rd_next = 5'bz;
                funct3_next = instruction[14:12];
                funct7_next = instruction[31:25];
            end

            default: begin
                decoded_value_next = 32'bz;
                rs1_next = 5'b0;
                rs2_next = 5'bz;
                rd_next = 5'b0;
                opcode_next = `INST_I_ALU;
                funct3_next = `ADDI_FUNCT3;
                funct7_next = 7'b0;
            end
        endcase
    end

    initial begin
        opcode_reg = 7'b0;
        funct3_reg = 3'b0;
        funct7_reg = 3'b0;
        decoded_value_reg = 32'bz;
        rs1_reg = 5'bz;
        rs2_reg = 5'bz;
        rd_reg = 5'bz;  
        trap_reg = 1'b0;
        shift_la_sel_reg = 1'bz;
        e_call_break_reg = 1'bz;
        pred_succ_reg = 8'bz;
    end

endmodule

tb/rv32_decoder_tb.v
`timescale 1ns/1ps
`include "../core/rv32_decoder.v"

module decoder_tb();

    reg clk;
    reg [31:0] instruction;

    wire [31:0] decoded_value;
    wire [4:0] rs1, rs2, rd;
    wire [6:0] opcode;
    wire [2:0] funct3;
    wire [6:0] funct7;
    wire shift_la_sel, trap;
    wire e_call_break;
    wire [7:0] pred_succ;

    decoder uut(
        .clk(clk),
        .instruction(instruction),
        .decoded_value(decoded_value),
        .rs1(rs1),
        .rs2(rs2),
        .rd(rd),
        .opcode(opcode),
        .funct3(funct3),
        .funct7(funct7),
        .shift_la_sel(shift_la_sel),
        .trap(trap),
        .e_call_break(e_call_break),
        .pred_succ(pred_succ)
    );

    localparam PERIOD = 10;

    always
    #(PERIOD/2) clk = ~clk;

    initial begin
        clk = 1'b0;

        instruction = 32'habcde237; // lui x4,0xabcde
        #(PERIOD);
        instruction = 32'habcde217; // auipc x4,0xabcde
        #(PERIOD);
        instruction = 32'h004000ef; // jal x1,0x0000000c
        #(PERIOD);
        instruction = 32'h00808267; // jalr x4,8(x1)
        #(PERIOD);
        instruction = 32'hff808267; // jalr x4,-8(x1)
        #(PERIOD);
        instruction = 32'h00000263; // beq x0,x0,0x00000018
        #(PERIOD);
        instruction = 32'hfe001ee3; // bne x0,x0,0x00000014
        #(PERIOD);
        instruction = 32'h00004263; // blt x0,x0,0x00000020
        #(PERIOD);
        instruction = 32'h00005263; // bge x0,x0,0x00000024
        #(PERIOD);
        instruction = 32'h00006263; // bltu x0,x0,0x00000028
        #(PERIOD);
        instruction = 32'h00007263; // bgeu x0,x0,0x0000002c
        #(PERIOD);
        instruction = 32'h4d200203; // lb x4,1234(x0)
        #(PERIOD);
        instruction = 32'hb2e01203; // lh x4,-1234(x0)
        #(PERIOD);
        instruction = 32'h4d202203; // lw x4,1234(x0)
        #(PERIOD);
        instruction = 32'h80004203; // lbu x4,-2048(x0)
        #(PERIOD);
        instruction = 32'h00005203; // lhu x4,0(x0)
        #(PERIOD);
        instruction = 32'h4c400923; // sb x4,1234(x0)
        #(PERIOD);
        instruction = 32'h4c401923; // sh x4,1234(x0)
        #(PERIOD);
        instruction = 32'h4c402923; // sw x4,1234(x0)
        #(PERIOD);
        instruction = 32'h4d228213; // addi x4,x5,1234
        #(PERIOD);
        instruction = 32'hfff3a313; // slti x6,x7,-1
        #(PERIOD);
        instruction = 32'h8304b413; // sltiu x8,x9,-2000
        #(PERIOD);
        instruction = 32'h0015c513; // xori x10,x11,1
        #(PERIOD);
        instruction = 32'h7d06e613; // ori x12,x13,2000
        #(PERIOD);
        instruction = 32'h4d27f713; // andi x14,x15,1234
        #(PERIOD);
        instruction = 32'h00c89813; // slli x16,x17,12
        #(PERIOD);
        instruction = 32'h00c9d913; // srli x18,x19,12
        #(PERIOD);
        instruction = 32'h40cada13; // srai x20,x21,12
        #(PERIOD);
        instruction = 32'h018b8b33; // add x22,x23,x24
        #(PERIOD);
        instruction = 32'h41bd0cb3; // sub x25,x26,x27
        #(PERIOD);
        instruction = 32'h01ee9e33; // sll x28,x29,x30
        #(PERIOD);
        instruction = 32'h0020afb3; // slt x31,x1,x2
        #(PERIOD);
        instruction = 32'h0020b233; // sltu x4,x1,x2
        #(PERIOD);
        instruction = 32'h0020c233; // xor x4,x1,x2
        #(PERIOD);
        instruction = 32'h0042d1b3; // srl x3,x5,x4
        #(PERIOD);
        instruction = 32'h4042d1b3; // sra x3,x5,x4
        #(PERIOD);
        instruction = 32'h0020e233; // or x4,x1,x2
        #(PERIOD);
        instruction = 32'h0020f233; // and x4,x1,x2
        #(PERIOD);
        instruction = 32'h000b1a73; // csrrw x20,0x000,x22
        #(PERIOD);
        instruction = 32'h001cabf3; // csrrs x23,0x001,x25
        #(PERIOD);
        instruction = 32'h002e3d73; // csrrc x26,0x002,x28
        #(PERIOD);
        instruction = 32'hfff55ef3; // csrrwi x29,0xfff,10
        #(PERIOD);
        instruction = 32'h10066f73; // csrrsi x30,0x100,12
        #(PERIOD);
        instruction = 32'h00177ff3; // csrrci x31,0x001,14
        #(PERIOD);
        instruction = 32'h001ffff3; // csrrci x31,0x001,31
        #(PERIOD);
        instruction = 32'h00100073; // ebreak
        #(PERIOD);
        instruction = 32'h00000073; // ecall
        #(PERIOD);
        instruction = 32'ha5a5a5a5; // ERROR: UNIMPLEMENTED INSTRUCTION
        #(PERIOD);

        #(PERIOD*4);
        $finish;
    end

    initial begin
        $dumpfile("../waveforms/rv32_decoder_tb.vcd");
        $dumpvars();
    end

endmodule

waveforms/rv32_decoder_tb.vcd
$date
	Mon Jan 23 21:32:27 2023
$end
$version
	Icarus Verilog
$end
$timescale
	1ps
$end
$scope module decoder_tb $end
$var wire 1 ! trap $end
$var wire 1 " shift_la_sel $end
$var wire 5 # rs2 [4:0] $end
$var wire 5 $ rs1 [4:0] $end
$var wire 5 % rd [4:0] $end
$var wire 8 & pred_succ [7:0] $end
$var wire 7 ' opcode [6:0] $end
$var wire 7 ( funct7 [6:0] $end
$var wire 3 ) funct3 [2:0] $end
$var wire 1 * e_call_break $end
$var wire 32 + decoded_value [31:0] $end
$var parameter 32 , PERIOD $end
$var reg 1 - clk $end
$var reg 32 . instruction [31:0] $end
$scope module uut $end
$var wire 1 - clk $end
$var wire 32 / decoded_value [31:0] $end
$var wire 1 * e_call_break $end
$var wire 3 0 funct3 [2:0] $end
$var wire 7 1 funct7 [6:0] $end
$var wire 32 2 instruction [31:0] $end
$var wire 7 3 opcode [6:0] $end
$var wire 8 4 pred_succ [7:0] $end
$var wire 5 5 rd [4:0] $end
$var wire 5 6 rs1 [4:0] $end
$var wire 5 7 rs2 [4:0] $end
$var wire 1 " shift_la_sel $end
$var wire 1 ! trap $end
$var wire 3 8 instruction_type [2:0] $end
$var parameter 3 9 B_TYPE $end
$var parameter 3 : I_TYPE $end
$var parameter 3 ; J_TYPE $end
$var parameter 3 < R_TYPE $end
$var parameter 3 = S_TYPE $end
$var parameter 3 > U_TYPE $end
$var reg 32 ? decoded_value_next [31:0] $end
$var reg 32 @ decoded_value_reg [31:0] $end
$var reg 1 A e_call_break_reg $end
$var reg 3 B funct3_next [2:0] $end
$var reg 3 C funct3_reg [2:0] $end
$var reg 7 D funct7_next [6:0] $end
$var reg 7 E funct7_reg [6:0] $end
$var reg 7 F opcode_next [6:0] $end
$var reg 7 G opcode_reg [6:0] $end
$var reg 8 H pred_succ_reg [7:0] $end
$var reg 5 I rd_next [4:0] $end
$var reg 5 J rd_reg [4:0] $end
$var reg 5 K rs1_next [4:0] $end
$var reg 5 L rs1_reg [4:0] $end
$var reg 5 M rs2_next [4:0] $end
$var reg 5 N rs2_reg [4:0] $end
$var reg 1 O shift_la_sel_reg $end
$var reg 1 P trap_reg $end
$upscope $end
$upscope $end
$enddefinitions $end
$comment Show the parameter values. $end
$dumpall
b11 >
b10 =
b0 <
b100 ;
b1 :
b111 9
b1010 ,
$end
#0
$dumpvars
0P
zO
bz N
bz M
bz L
bz K
bz J
b100 I
bz H
b0 G
b110111 F
b0 E
bz D
b0 C
bz B
zA
bz @
b10101011110011011110000000000000 ?
b11 8
bz 7
bz 6
bz 5
bz 4
b0 3
b10101011110011011110001000110111 2
b0 1
b0 0
bz /
b10101011110011011110001000110111 .
0-
bz +
z*
b0 )
b0 (
b0 '
bz &
bz %
bz $
bz #
z"
0!
$end
#5000
bz (
bz 1
bz E
bz )
bz 0
bz C
b110111 '
b110111 3
b110111 G
b100 %
b100 5
b100 J
b10101011110011011110000000000000 +
b10101011110011011110000000000000 /
b10101011110011011110000000000000 @
1-
#10000
b10111 F
0-
b10101011110011011110001000010111 .
b10101011110011011110001000010111 2
#15000
b10111 '
b10111 3
b10111 G
1-
#20000
b100 8
b1 I
b100 ?
b1101111 F
0-
b10000000000000011101111 .
b10000000000000011101111 2
#25000
b1101111 '
b1101111 3
b1101111 G
b1 %
b1 5
b1 J
b100 +
b100 /
b100 @
1-
#30000
bz D
b0 B
b1 K
b1 8
b100 I
b1000 ?
b1100111 F
0-
b100000001000001001100111 .
b100000001000001001100111 2
#35000
b0 )
b0 0
b0 C
b1100111 '
b1100111 3
b1100111 G
b100 %
b100 5
b100 J
b1 $
b1 6
b1 L
b1000 +
b1000 /
b1000 @
1-
#40000
b11111111111111111111111111111000 ?
0-
b11111111100000001000001001100111 .
b11111111100000001000001001100111 2
#45000
b11111111111111111111111111111000 +
b11111111111111111111111111111000 /
b11111111111111111111111111111000 @
1-
#50000
b0 D
bz I
b0 M
b0 K
b100 ?
b111 8
b1100011 F
0-
b1001100011 .
b1001100011 2
#55000
b0 (
b0 1
b0 E
b1100011 '
b1100011 3
b1100011 G
bz %
bz 5
bz J
b0 #
b0 7
b0 N
b0 $
b0 6
b0 L
b100 +
b100 /
b100 @
1-
#60000
b1111111 D
b1 B
b11111111111111111111111111111100 ?
0-
b11111110000000000001111011100011 .
b11111110000000000001111011100011 2
#65000
b1111111 (
b1111111 1
b1111111 E
b1 )
b1 0
b1 C
b11111111111111111111111111111100 +
b11111111111111111111111111111100 /
b11111111111111111111111111111100 @
1-
#70000
b0 D
b100 B
b100 ?
0-
b100001001100011 .
b100001001100011 2
#75000
b0 (
b0 1
b0 E
b100 )
b100 0
b100 C
b100 +
b100 /
b100 @
1-
#80000
b101 B
0-
b101001001100011 .
b101001001100011 2
#85000
b101 )
b101 0
b101 C
1-
#90000
b110 B
0-
b110001001100011 .
b110001001100011 2
#95000
b110 )
b110 0
b110 C
1-
#100000
b111 B
0-
b111001001100011 .
b111001001100011 2
#105000
b111 )
b111 0
b111 C
1-
#110000
b100 I
b1 8
bz D
b0 B
bz M
b10011010010 ?
b11 F
0-
b1001101001000000000001000000011 .
b1001101001000000000001000000011 2
#115000
bz (
bz 1
bz E
b0 )
b0 0
b0 C
b11 '
b11 3
b11 G
b100 %
b100 5
b100 J
bz #
bz 7
bz N
b10011010010 +
b10011010010 /
b10011010010 @
1-
#120000
b1 B
b11111111111111111111101100101110 ?
0-
b10110010111000000001001000000011 .
b10110010111000000001001000000011 2
#125000
b1 )
b1 0
b1 C
b11111111111111111111101100101110 +
b11111111111111111111101100101110 /
b11111111111111111111101100101110 @
1-
#130000
b10 B
b10011010010 ?
0-
b1001101001000000010001000000011 .
b1001101001000000010001000000011 2
#135000
b10 )
b10 0
b10 C
b10011010010 +
b10011010010 /
b10011010010 @
1-
#140000
b100 B
b11111111111111111111100000000000 ?
0-
b10000000000000000100001000000011 .
b10000000000000000100001000000011 2
#145000
b100 )
b100 0
b100 C
b11111111111111111111100000000000 +
b11111111111111111111100000000000 /
b11111111111111111111100000000000 @
1-
#150000
b101 B
b0 ?
0-
b101001000000011 .
b101001000000011 2
#155000
b101 )
b101 0
b101 C
b0 +
b0 /
b0 @
1-
#160000
b100011 F
0-
b1001100010000000000100100100011 .
b1001100010000000000100100100011 2
#165000
b100011 '
b100011 3
b100011 G
1-
#170000
0-
b1001100010000000001100100100011 .
b1001100010000000001100100100011 2
#175000
1-
#180000
0-
b1001100010000000010100100100011 .
b1001100010000000010100100100011 2
#185000
1-
#190000
bz D
b100 I
b1 8
b0 B
b101 K
b10011010010 ?
b10011 F
0-
b1001101001000101000001000010011 .
b1001101001000101000001000010011 2
#195000
b0 )
b0 0
b0 C
b10011 '
b10011 3
b10011 G
b101 $
b101 6
b101 L
b10011010010 +
b10011010010 /
b10011010010 @
1-
#200000
b10 B
b110 I
b111 K
b11111111111111111111111111111111 ?
0-
b11111111111100111010001100010011 .
b11111111111100111010001100010011 2
#205000
b10 )
b10 0
b10 C
b110 %
b110 5
b110 J
b111 $
b111 6
b111 L
b11111111111111111111111111111111 +
b11111111111111111111111111111111 /
b11111111111111111111111111111111 @
1-
#210000
b11 B
b1000 I
b1001 K
b11111111111111111111100000110000 ?
0-
b10000011000001001011010000010011 .
b10000011000001001011010000010011 2
#215000
b11 )
b11 0
b11 C
b1000 %
b1000 5
b1000 J
b1001 $
b1001 6
b1001 L
b11111111111111111111100000110000 +
b11111111111111111111100000110000 /
b11111111111111111111100000110000 @
1-
#220000
b100 B
b1010 I
b1011 K
b1 ?
0-
b101011100010100010011 .
b101011100010100010011 2
#225000
b100 )
b100 0
b100 C
b1010 %
b1010 5
b1010 J
b1011 $
b1011 6
b1011 L
b1 +
b1 /
b1 @
1-
#230000
b110 B
b1100 I
b1101 K
b11111010000 ?
0-
b1111101000001101110011000010011 .
b1111101000001101110011000010011 2
#235000
b110 )
b110 0
b110 C
b1100 %
b1100 5
b1100 J
b1101 $
b1101 6
b1101 L
b11111010000 +
b11111010000 /
b11111010000 @
1-
#240000
b111 B
b1110 I
b1111 K
b10011010010 ?
0-
b1001101001001111111011100010011 .
b1001101001001111111011100010011 2
#245000
b111 )
b111 0
b111 C
b1110 %
b1110 5
b1110 J
b1111 $
b1111 6
b1111 L
b10011010010 +
b10011010010 /
b10011010010 @
1-
#250000
b1 B
b10000 I
b10001 K
b1100 ?
0-
b110010001001100000010011 .
b110010001001100000010011 2
#255000
b1 )
b1 0
b1 C
b10000 %
b10000 5
b10000 J
b10001 $
b10001 6
b10001 L
b1100 +
b1100 /
b1100 @
1-
#260000
b101 B
b10010 I
b10011 K
0-
b110010011101100100010011 .
b110010011101100100010011 2
#265000
b101 )
b101 0
b101 C
b10010 %
b10010 5
b10010 J
b10011 $
b10011 6
b10011 L
1-
#270000
b10100 I
b10101 K
b10000001100 ?
0-
b1000000110010101101101000010011 .
b1000000110010101101101000010011 2
#275000
b10100 %
b10100 5
b10100 J
b10101 $
b10101 6
b10101 L
b10000001100 +
b10000001100 /
b10000001100 @
1-
#280000
b0 D
b0 B
b10110 I
b11000 M
b10111 K
bz ?
b0 8
b110011 F
0-
b1100010111000101100110011 .
b1100010111000101100110011 2
#285000
b0 (
b0 1
b0 E
b0 )
b0 0
b0 C
b110011 '
b110011 3
b110011 G
b10110 %
b10110 5
b10110 J
b11000 #
b11000 7
b11000 N
b10111 $
b10111 6
b10111 L
bz +
bz /
bz @
1-
#290000
b100000 D
b11001 I
b11011 M
b11010 K
0-
b1000001101111010000110010110011 .
b1000001101111010000110010110011 2
#295000
b100000 (
b100000 1
b100000 E
b11001 %
b11001 5
b11001 J
b11011 #
b11011 7
b11011 N
b11010 $
b11010 6
b11010 L
1-
#300000
b0 D
b1 B
b11100 I
b11110 M
b11101 K
0-
b1111011101001111000110011 .
b1111011101001111000110011 2
#305000
b0 (
b0 1
b0 E
b1 )
b1 0
b1 C
b11100 %
b11100 5
b11100 J
b11110 #
b11110 7
b11110 N
b11101 $
b11101 6
b11101 L
1-
#310000
b10 B
b11111 I
b10 M
b1 K
0-
b1000001010111110110011 .
b1000001010111110110011 2
#315000
b10 )
b10 0
b10 C
b11111 %
b11111 5
b11111 J
b10 #
b10 7
b10 N
b1 $
b1 6
b1 L
1-
#320000
b11 B
b100 I
0-
b1000001011001000110011 .
b1000001011001000110011 2
#325000
b11 )
b11 0
b11 C
b100 %
b100 5
b100 J
1-
#330000
b100 B
0-
b1000001100001000110011 .
b1000001100001000110011 2
#335000
b100 )
b100 0
b100 C
1-
#340000
b101 B
b11 I
b100 M
b101 K
0-
b10000101101000110110011 .
b10000101101000110110011 2
#345000
b101 )
b101 0
b101 C
b11 %
b11 5
b11 J
b100 #
b100 7
b100 N
b101 $
b101 6
b101 L
1-
#350000
b100000 D
0-
b1000000010000101101000110110011 .
b1000000010000101101000110110011 2
#355000
b100000 (
b100000 1
b100000 E
1-
#360000
b0 D
b110 B
b100 I
b10 M
b1 K
0-
b1000001110001000110011 .
b1000001110001000110011 2
#365000
b0 (
b0 1
b0 E
b110 )
b110 0
b110 C
b100 %
b100 5
b100 J
b10 #
b10 7
b10 N
b1 $
b1 6
b1 L
1-
#370000
b111 B
0-
b1000001111001000110011 .
b1000001111001000110011 2
#375000
b111 )
b111 0
b111 C
1-
#380000
b0 ?
b1 8
b0 B
b0 I
bz M
b0 K
b1110011 F
0-
b10110001101001110011 .
b10110001101001110011 2
#385000
1!
1P
b0 )
b0 0
b0 C
b1110011 '
b1110011 3
b1110011 G
b0 %
b0 5
b0 J
bz #
bz 7
bz N
b0 $
b0 6
b0 L
b0 +
b0 /
b0 @
1-
#390000
b1 ?
0-
b111001010101111110011 .
b111001010101111110011 2
#395000
b1 +
b1 /
b1 @
1-
#400000
b10 ?
0-
b1011100011110101110011 .
b1011100011110101110011 2
#405000
b10 +
b10 /
b10 @
1-
#410000
b1010 ?
0-
b11111111111101010101111011110011 .
b11111111111101010101111011110011 2
#415000
b1010 +
b1010 /
b1010 @
1-
#420000
b1100 ?
0-
b10000000001100110111101110011 .
b10000000001100110111101110011 2
#425000
b1100 +
b1100 /
b1100 @
1-
#430000
b1110 ?
0-
b101110111111111110011 .
b101110111111111110011 2
#435000
b1110 +
b1110 /
b1110 @
1-
#440000
b11111 ?
0-
b111111111111111110011 .
b111111111111111110011 2
#445000
b11111 +
b11111 /
b11111 @
1-
#450000
bz D
0-
b100000000000001110011 .
b100000000000001110011 2
#455000
1*
1A
bz (
bz 1
bz E
1-
#460000
0-
b1110011 .
b1110011 2
#465000
0*
0A
1-
#470000
b0 D
bz ?
bz 8
b10011 F
0-
b10100101101001011010010110100101 .
b10100101101001011010010110100101 2
#475000
z*
zA
b0 (
b0 1
b0 E
b10011 '
b10011 3
b10011 G
bz +
bz /
bz @
1-
#480000
0-
#485000
0"
0O
1-
